pyschedge/SchedgeException.py
pyschedge/__init__.py
pyschedge/pyschedge.py
pyschedge-0.0.1.dist-info/LICENSE
pyschedge-0.0.1.dist-info/METADATA
pyschedge-0.0.1.dist-info/WHEEL
pyschedge-0.0.1.dist-info/top_level.txt
pyschedge-0.0.1.dist-info/RECORD
