Metadata-Version: 2.1
Name: pyschedge
Version: 0.0.1
Summary: A light weight Python wrapper for the Schedge API
Home-page: https://github.com/Kn99HN/pyschedge
Author: @Kn99HN
Author-email: khanhnguyen99hn@gmail.com
License: MIT
Platform: UNKNOWN
Requires-Dist: requests
